vivabem/__init__.py
vivabem/main.py
vivabem-0.0.6.dist-info/licenses/LICENSE
vivabem-0.0.6.dist-info/WHEEL
vivabem-0.0.6.dist-info/METADATA
vivabem-0.0.6.dist-info/RECORD
