Metadata-Version: 2.4
Name: vivabem
Version: 0.0.6
Summary: Base shared class for loading data from smartwatches collected for the VivaBem project.
Author-email: Rafael Ito <ito.rafael@gmail.com>
License-File: LICENSE
